[
  {
    "id": "1978883672452534405#m",
    "link": "https://x.com/Nillioneco/status/1978883672452534405#m",
    "author": "@Nillioneco"
  },
  {
    "id": "1979247538361504253#m",
    "link": "https://x.com/buildonnillion/status/1979247538361504253#m",
    "author": "@buildonnillion"
  },
  {
    "id": "1979205255213527243#m",
    "link": "https://x.com/Pindora_HQ/status/1979205255213527243#m",
    "author": "@Pindora_HQ"
  },
  {
    "id": "1975914776963252592#m",
    "link": "https://x.com/soar_chain/status/1975914776963252592#m",
    "author": "@soar_chain"
  },
  {
    "id": "1979168257387925557#m",
    "link": "https://x.com/HealthBlocks/status/1979168257387925557#m",
    "author": "@HealthBlocks"
  },
  {
    "id": "1975339604241694954#m",
    "link": "https://x.com/SkillfulAI/status/1975339604241694954#m",
    "author": "@SkillfulAI"
  },
  {
    "id": "1978828432113832260#m",
    "link": "https://x.com/FulcraDynamics/status/1978828432113832260#m",
    "author": "@FulcraDynamics"
  },
  {
    "id": "1979199694556340643#m",
    "link": "https://x.com/MonadicDNA/status/1979199694556340643#m",
    "author": "@MonadicDNA"
  },
  {
    "id": "1957925684816577022#m",
    "link": "https://x.com/StadiumScience_/status/1957925684816577022#m",
    "author": "@StadiumScience_"
  },
  {
    "id": "1978525028539908583#m",
    "link": "https://x.com/rainfall_one/status/1978525028539908583#m",
    "author": "@rainfall_one"
  },
  {
    "id": "1979203802390806976#m",
    "link": "https://x.com/0xCapx/status/1979203802390806976#m",
    "author": "@0xCapx"
  },
  {
    "id": "1909265929151603074#m",
    "link": "https://x.com/soda_fun/status/1909265929151603074#m",
    "author": "@soda_fun"
  },
  {
    "id": "1979191444624806134#m",
    "link": "https://x.com/LingoAI_io/status/1979191444624806134#m",
    "author": "@LingoAI_io"
  }
]